qb_bot/__init__.py
qb_bot/api.py
qb_bot/exceptions.py
qb_bot_sdk-0.1.0.dist-info/METADATA
qb_bot_sdk-0.1.0.dist-info/WHEEL
qb_bot_sdk-0.1.0.dist-info/top_level.txt
qb_bot_sdk-0.1.0.dist-info/RECORD
